{
  "الذكر عند الخروج من المنزل": {
    "text": [
      "بسم الله ، توكَّلْتُ على الله ، ولا حَوْلَ ولا قُوةَ إلا بالله ",
      "اللهُمَ إني أعُوذُ بِكَ أن أَضِلَّ أوْ أُضَلَّ أَوْ أزِلَّ، أو أُزَلَّ، أوْ أظلِم أوْ أُظْلَم، أوْ أَجْهَلَ أوْ يُجْهَلَ عَلَيَّ "
    ],
    "footnote": [
      " أبو داود 4/ 325 والترمذي 5/ 490 وانظر صحيح الترمذي 3/ 151",
      "أهل السنن وانظر صحيح الترمذي 3/ 152 وصحيح ابن ماجه 2/ 336"
    ]
  },
  "الذكر عند الدخول المنزل": {
    "text": [
      "بسم الله ولجنا ،وبسم الله خرجنا ، وعلى ربنا توكلنا ، ثم ليسلم على أهله"
    ],
    "footnote": [
      "أخرجه أبو داود 4/ 325 ، وحسن إسناده العلامة ابن باز في تحفة الأخيار ص28 ، وفي الصحيح  إذا دخل الرجل بيته فذكر بيته فذكر الله عند دخوله وعند طعامه قال الشيطان لا مبيت لكم ولا عشاء  مسلم برقم 2018"
    ]
  }
}